glwindow.cpython-38-x86_64-linux-gnu.so
glwindow-4.2.0.dist-info/WHEEL
glwindow-4.2.0.dist-info/top_level.txt
glwindow-4.2.0.dist-info/RECORD
glwindow-4.2.0.dist-info/METADATA
glwindow-4.2.0.dist-info/LICENSE
