Metadata-Version: 2.1
Name: glwindow
Version: 4.2.0
Summary: A simple window with your own main loop.
Home-page: https://github.com/glnext/glwindow/
Author: Szabolcs Dombi
Author-email: cprogrammer1994@gmail.com
License: MIT
Platform: UNKNOWN
